jotting/__init__.py
jotting/_book_py27.py
jotting/_book_py35.py
jotting/_shelf_py27.py
jotting/_shelf_py35.py
jotting/book.py
jotting/dist.py
jotting/read.py
jotting/shelf.py
jotting/style.py
jotting/to.py
jotting/util.py
jotting/utils.py
jotting/via.py
jotting/write/__init__.py
jotting/write/mixin.py
jotting/write/process.py
jotting/write/thread.py
jotting-0.2.0.dist-info/DESCRIPTION.rst
jotting-0.2.0.dist-info/METADATA
jotting-0.2.0.dist-info/RECORD
jotting-0.2.0.dist-info/WHEEL
jotting-0.2.0.dist-info/metadata.json
jotting-0.2.0.dist-info/top_level.txt
